PDBNucleicAcids/BasePairRules.py
PDBNucleicAcids/Geometry.py
PDBNucleicAcids/NucleicAcid.py
PDBNucleicAcids/__init__.py
pdbnucleicacids-0.3.5.dist-info/licenses/AUTHORS.rst
pdbnucleicacids-0.3.5.dist-info/licenses/LICENSE
pdbnucleicacids-0.3.5.dist-info/METADATA
pdbnucleicacids-0.3.5.dist-info/WHEEL
pdbnucleicacids-0.3.5.dist-info/top_level.txt
pdbnucleicacids-0.3.5.dist-info/RECORD
