Metadata-Version: 2.4
Name: pdbnucleicacids
Version: 0.3.5
Summary: A Biopython based package that constructs and represent all nucleic acids in a PDB structure, with a special focus on base-pair representation.
Author-email: Alessandro Pandolfi <alessandro.pandolfi@protonmail.com>
Maintainer-email: Alessandro Pandolfi <alessandro.pandolfi@protonmail.com>
License: MIT license
Project-URL: bugs, https://gitlab.com/MorfeoRenai/pdbnucleicacids/-/issues
Project-URL: changelog, https://gitlab.com/MorfeoRenai/pdbnucleicacids/-/blob/main/HISTORY.rst
Project-URL: homepage, https://gitlab.com/MorfeoRenai/pdbnucleicacids
Classifier: Programming Language :: Python :: 3
Requires-Python: >=3.10
License-File: LICENSE
License-File: AUTHORS.rst
Requires-Dist: numpy
Requires-Dist: pandas
Requires-Dist: biopython
Provides-Extra: dev
Requires-Dist: pip; extra == "dev"
Requires-Dist: spyder-kernels; extra == "dev"
Requires-Dist: flake8; extra == "dev"
Requires-Dist: ruff; extra == "dev"
Requires-Dist: mypy; extra == "dev"
Requires-Dist: pytest; extra == "dev"
Requires-Dist: tox; extra == "dev"
Requires-Dist: coverage; extra == "dev"
Requires-Dist: sphinx; extra == "dev"
Requires-Dist: watchdog; extra == "dev"
Requires-Dist: bump-my-version; extra == "dev"
Requires-Dist: wheel; extra == "dev"
Requires-Dist: build; extra == "dev"
Requires-Dist: twine; extra == "dev"
Dynamic: license-file
